testing123KK/__init__.py
testing123kk-10.0.5.dist-info/METADATA
testing123kk-10.0.5.dist-info/WHEEL
testing123kk-10.0.5.dist-info/top_level.txt
testing123kk-10.0.5.dist-info/RECORD
